lockhart_serial/__init__.py
lockhart_serial/lockhart_serial.py
lockhart_serial-1.0.8.dist-info/METADATA
lockhart_serial-1.0.8.dist-info/WHEEL
lockhart_serial-1.0.8.dist-info/licenses/LICENSE
lockhart_serial-1.0.8.dist-info/RECORD
