Metadata-Version: 2.3
Name: lockhart-serial
Version: 1.0.8
Summary: Serial communication for Lockhart devices
Project-URL: Homepage, https://github.com/pypa/sampleproject
Project-URL: Issues, https://github.com/pypa/sampleproject/issues
Author-email: NinjaBunny <xxninjabunnyxx@gmail.com>
License-File: LICENSE
Classifier: License :: OSI Approved :: MIT License
Classifier: Operating System :: OS Independent
Classifier: Programming Language :: Python :: 3
Requires-Python: >=3.8
Requires-Dist: pyserial
